mcp_time_service1/__init__.py
mcp_time_service1/__main__.py
mcp_time_service1-0.1.0.dist-info/licenses/LICENSE
mcp_time_service1-0.1.0.dist-info/METADATA
mcp_time_service1-0.1.0.dist-info/WHEEL
mcp_time_service1-0.1.0.dist-info/entry_points.txt
mcp_time_service1-0.1.0.dist-info/top_level.txt
mcp_time_service1-0.1.0.dist-info/RECORD
